barcode_splitter.py
barcode_splitter-0.18.6.dist-info/METADATA
barcode_splitter-0.18.6.dist-info/RECORD
barcode_splitter-0.18.6.dist-info/WHEEL
barcode_splitter-0.18.6.dist-info/entry_points.txt
barcode_splitter-0.18.6.dist-info/top_level.txt
