Metadata-Version: 2.1
Name: barcode-splitter
Version: 0.18.6
Summary: A utility to split multiple sequence files using multiple sets of barcodes
Home-page: https://bitbucket.org/princeton_genomics/barcode_splitter
Author: Robert Leach, Lance Parsons
Author-email: rleach@princeton.edu, lparsons@princeton.edu
License: BSD 2-clause
Keywords: sequencing fastq paired barcode demultiplex
Platform: UNKNOWN
Classifier: Development Status :: 4 - Beta
Classifier: Intended Audience :: Science/Research
Classifier: Topic :: Scientific/Engineering :: Bio-Informatics
Classifier: License :: OSI Approved :: BSD License
Classifier: Programming Language :: Python :: 2
Classifier: Programming Language :: Python :: 2.6
Classifier: Programming Language :: Python :: 2.7
Classifier: Programming Language :: Python :: 3
Classifier: Programming Language :: Python :: 3.1
Classifier: Programming Language :: Python :: 3.3
Classifier: Programming Language :: Python :: 3.4
Classifier: Programming Language :: Python :: 3.5
Classifier: Programming Language :: Python :: 3.6
Classifier: Programming Language :: Python :: 3.7
Provides-Extra: test
Provides-Extra: dev
Requires-Dist: ordereddict (>=1.1); python_version < "2.7"
Requires-Dist: argparse; python_version < "2.7"
Provides-Extra: dev
Requires-Dist: check-manifest; extra == 'dev'
Requires-Dist: flake8; extra == 'dev'
Provides-Extra: test
Requires-Dist: tox; extra == 'test'
